README.md
tokesim/__init__.py
tokesim/__main__.py
tokesim/accounts.json
tokesim/agents/__init__.py
tokesim/agents/ethereum_agent.py
tokesim/client/__init__.py
tokesim/client/client_util.py
tokesim/client/generated_types.py
tokesim/client/tokesim.py
tokesim/commands/commandline.py
tokesim/commands/initialize.py
tokesim/commands/run.py
tokesim/config/__init__.py
tokesim/config/config_parser.py
tokesim/config/config_schema.json
tokesim/config/configuration.py
tokesim/config/ethereum_config.py
tokesim/config/model_config.py
tokesim/models/__init__.py
tokesim/models/ethereum_model.py
tokesim/models/model.py
tokesim/models/old_contract_model
tokesim/models/old_ethereum_contract_model
tokesim/simulation/__init__.py
tokesim/simulation/server.py
tokesim/simulation/sim.py
tokesim/template/__init__.py
tokesim/template/ethereum/__init__.py
tokesim/template/ethereum/contracts/SimpleToken.bin
tokesim/template/ethereum/contracts/SimpleToken_abi.json
tokesim/template/ethereum/contracts/__init__.py
tokesim/template/ethereum/contracts/oldSimpleToken.bin
tokesim/template/ethereum/contracts/oldSimpleToken_abi.json
tokesim/template/ethereum/generator.py
tokesim/template/ethereum/old_simple_token_model
tokesim/template/ethereum/simple_token_agent.py
tokesim/template/ethereum/simple_token_config.py
tokesim/template/ethereum/simple_token_dashboard.py
tokesim/template/ethereum/simple_token_model.py
tokesim/template/generator.py
tokesim/util/__init__.py
tokesim/util/utils.py
tokesim/visualizations/SimpleContinuousModule.py
tokesim/visualizations/__init__.py
tokesim/visualizations/dashboard.py
tokesim/visualizations/simple_continuous_canvas.js
tokesim-0.1.0.dist-info/entry_points.txt
tokesim-0.1.0.dist-info/LICENSE
tokesim-0.1.0.dist-info/WHEEL
tokesim-0.1.0.dist-info/METADATA
tokesim-0.1.0.dist-info/RECORD
