Metadata-Version: 2.1
Name: tokesim
Version: 0.1.0
Summary: A tool for building shareable Multi-Agent tokenomic models
Home-page: https://github.com/tokesim/mesa_behaviors
Keywords: mesa,blockchain,tokesim,simulation,agent,modeling,mulit-agent,tokens
Author: Zane Starr
Author-email: zcstarr@gmail.com
Requires-Python: >=3.7,<3.8
Classifier: Intended Audience :: Developers
Classifier: License :: OSI Approved :: Apache Software License
Classifier: Natural Language :: English
Classifier: Operating System :: OS Independent
Classifier: Programming Language :: Python
Classifier: Programming Language :: Python :: 3
Classifier: Programming Language :: Python :: 3 :: Only
Classifier: Programming Language :: Python :: 3.7
Classifier: Programming Language :: Python :: 3.8
Classifier: Topic :: Scientific/Engineering
Classifier: Topic :: Scientific/Engineering :: Artificial Intelligence
Classifier: Topic :: Scientific/Engineering :: Artificial Life
Requires-Dist: humps (>=0.2.2,<0.3.0)
Requires-Dist: jsonschema (>=3.2.0,<4.0.0)
Requires-Dist: mesa (>=0.8.6,<0.9.0)
Requires-Dist: mesa-behaviors (>=0.1.0,<0.2.0)
Requires-Dist: mypy_extensions (>=0.4.3,<0.5.0)
Requires-Dist: numpy (>=1.18.2,<2.0.0)
Requires-Dist: requests (>=2.23.0,<3.0.0)
Requires-Dist: web3 (>=5.7.0,<6.0.0)
Project-URL: Repository, https://github.com/tokesim/mesa_behaviors
